smolagents/__init__.py
smolagents/_function_type_hints_utils.py
smolagents/agent_types.py
smolagents/agents.py
smolagents/cli.py
smolagents/default_tools.py
smolagents/gradio_ui.py
smolagents/local_python_executor.py
smolagents/mcp_client.py
smolagents/memory.py
smolagents/models.py
smolagents/monitoring.py
smolagents/remote_executors.py
smolagents/tool_validation.py
smolagents/tools.py
smolagents/utils.py
smolagents/vision_web_browser.py
smolagents/prompts/code_agent.yaml
smolagents/prompts/structured_code_agent.yaml
smolagents/prompts/toolcalling_agent.yaml
smolagents_async-1.19.6.dist-info/licenses/LICENSE
smolagents_async-1.19.6.dist-info/METADATA
smolagents_async-1.19.6.dist-info/WHEEL
smolagents_async-1.19.6.dist-info/entry_points.txt
smolagents_async-1.19.6.dist-info/top_level.txt
smolagents_async-1.19.6.dist-info/RECORD
