Metadata-Version: 2.4
Name: smolagents-async
Version: 1.19.6
Summary: 🤗 smolagents-async: a clone of smolagents which supports asyncio.
Author-email: Aymeric Roucher <aymeric@hf.co>
Project-URL: Homepage, https://github.com/Newbluecake/smolagents-async
Project-URL: Source, https://github.com/Newbluecake/smolagents-async
Project-URL: Bug Tracker, https://github.com/Newbluecake/smolagents-async/issues
Requires-Python: >=3.10
License-File: LICENSE
Requires-Dist: huggingface-hub>=0.31.2
Requires-Dist: requests>=2.32.3
Requires-Dist: rich>=13.9.4
Requires-Dist: jinja2>=3.1.4
Requires-Dist: pillow>=10.0.1
Requires-Dist: python-dotenv
Provides-Extra: bedrock
Requires-Dist: boto3>=1.36.18; extra == "bedrock"
Provides-Extra: torch
Requires-Dist: torch; extra == "torch"
Requires-Dist: torchvision; extra == "torch"
Requires-Dist: numpy>=1.21.2; extra == "torch"
Provides-Extra: audio
Requires-Dist: soundfile; extra == "audio"
Requires-Dist: smolagents[torch]; extra == "audio"
Provides-Extra: docker
Requires-Dist: docker>=7.1.0; extra == "docker"
Requires-Dist: websocket-client; extra == "docker"
Provides-Extra: e2b
Requires-Dist: e2b-code-interpreter>=1.0.3; extra == "e2b"
Requires-Dist: python-dotenv>=1.0.1; extra == "e2b"
Provides-Extra: gradio
Requires-Dist: gradio>=5.14.0; extra == "gradio"
Provides-Extra: litellm
Requires-Dist: litellm>=1.60.2; extra == "litellm"
Provides-Extra: mcp
Requires-Dist: mcpadapt>=0.1.8; extra == "mcp"
Requires-Dist: mcp; extra == "mcp"
Provides-Extra: mlx-lm
Requires-Dist: mlx-lm; extra == "mlx-lm"
Provides-Extra: openai
Requires-Dist: openai>=1.58.1; extra == "openai"
Provides-Extra: telemetry
Requires-Dist: arize-phoenix; extra == "telemetry"
Requires-Dist: opentelemetry-sdk; extra == "telemetry"
Requires-Dist: opentelemetry-exporter-otlp; extra == "telemetry"
Requires-Dist: openinference-instrumentation-smolagents>=0.1.4; extra == "telemetry"
Provides-Extra: toolkit
Requires-Dist: duckduckgo-search>=6.3.7; extra == "toolkit"
Requires-Dist: markdownify>=0.14.1; extra == "toolkit"
Provides-Extra: transformers
Requires-Dist: accelerate; extra == "transformers"
Requires-Dist: transformers>=4.0.0; extra == "transformers"
Requires-Dist: smolagents[torch]; extra == "transformers"
Provides-Extra: vision
Requires-Dist: helium; extra == "vision"
Requires-Dist: selenium; extra == "vision"
Provides-Extra: vllm
Requires-Dist: vllm; extra == "vllm"
Requires-Dist: torch; extra == "vllm"
Provides-Extra: all
Requires-Dist: smolagents[audio,bedrock,docker,e2b,gradio,litellm,mcp,mlx-lm,openai,telemetry,toolkit,transformers,vision]; extra == "all"
Provides-Extra: quality
Requires-Dist: ruff>=0.9.0; extra == "quality"
Provides-Extra: test
Requires-Dist: ipython>=8.31.0; extra == "test"
Requires-Dist: pandas>=2.2.3; extra == "test"
Requires-Dist: pytest>=8.1.0; extra == "test"
Requires-Dist: pytest-datadir; extra == "test"
Requires-Dist: python-dotenv>=1.0.1; extra == "test"
Requires-Dist: smolagents[all]; extra == "test"
Requires-Dist: rank-bm25; extra == "test"
Requires-Dist: Wikipedia-API>=0.8.1; extra == "test"
Provides-Extra: dev
Requires-Dist: smolagents[quality,test]; extra == "dev"
Requires-Dist: sqlalchemy; extra == "dev"
Dynamic: license-file
